manganelo/__init__.py
manganelo/chapterdownload.py
manganelo/errors.py
manganelo/hometooltips.py
manganelo/httpclient.py
manganelo/storypage.py
manganelo/storysearch.py
manganelo/common/__init__.py
manganelo/common/constants.py
manganelo/common/utils.py
manganelo/models/__init__.py
manganelo/models/chapter.py
manganelo/models/homestorytooltip.py
manganelo/models/searchresult.py
manganelo/models/storypage.py
manganelo-1.23.dist-info/LICENSE.txt
manganelo-1.23.dist-info/METADATA
manganelo-1.23.dist-info/WHEEL
manganelo-1.23.dist-info/top_level.txt
manganelo-1.23.dist-info/RECORD
