Metadata-Version: 2.1
Name: manganelo
Version: 1.23
Summary: Unofficial API for the Manganelo/Manganato website.
Home-page: https://github.com/nixonjoshua98/manganelo
Download-URL: https://github.com/nixonjoshua98/manganelo/releases
Author: Joshua Nixon
Author-email: nixonjoshua98@gmail.com
License: MIT
Keywords: manga,manganelo,scrapper,web,mangakakalot,thread,comic,manhwa,manganato,manhwa
Classifier: Programming Language :: Python :: 3
Classifier: License :: OSI Approved :: MIT License
Classifier: Operating System :: OS Independent
Classifier: Development Status :: 5 - Production/Stable
Classifier: Intended Audience :: Developers
Classifier: Topic :: Software Development :: Build Tools
Requires-Python: >=3.9
License-File: LICENSE.txt
Requires-Dist: bs4
Requires-Dist: requests
Requires-Dist: reportlab
Requires-Dist: pillow
Requires-Dist: pydantic
